seam_carving/__init__.py
seam_carving/carve.py
seam_carving-1.1.0.dist-info/LICENSE
seam_carving-1.1.0.dist-info/METADATA
seam_carving-1.1.0.dist-info/WHEEL
seam_carving-1.1.0.dist-info/top_level.txt
seam_carving-1.1.0.dist-info/RECORD
