Metadata-Version: 2.1
Name: seam-carving
Version: 1.1.0
Summary: A super-fast Python implementation of seam carving algorithm for intelligent image resizing.
Home-page: https://github.com/li-plus/seam-carving
Author: Jiahao Li
Author-email: liplus17@163.com
Maintainer: Jiahao Li
Maintainer-email: liplus17@163.com
License: MIT
Keywords: seam carving,computer vision,image processing,image resizing,content aware
Classifier: Development Status :: 4 - Beta
Classifier: Intended Audience :: Science/Research
Classifier: Topic :: Scientific/Engineering :: Image Processing
Classifier: License :: OSI Approved :: MIT License
Classifier: Programming Language :: Python :: 3
Requires-Python: >=3.7
License-File: LICENSE
Requires-Dist: numpy
Requires-Dist: scipy
Requires-Dist: numba (>=0.56.0)
Provides-Extra: dev
Requires-Dist: Pillow ; extra == 'dev'
Requires-Dist: pytest ; extra == 'dev'
Requires-Dist: pytest-cov ; extra == 'dev'
Requires-Dist: isort ; extra == 'dev'
Requires-Dist: black ; extra == 'dev'
